[
{"餐厅名": "蜀锦香小郡肝串串香（武侯祠店）", "经度": 30.642262, "纬度": 104.043908, "图片": "https://img.meituan.net/msmerchant/9d2820c5fba77ae6cd1182422667f0fc427699.jpg", "depth": 2, "download_timeout": 180.0, "download_slot": "meishi.meituan.com", "download_latency": 0.09908151626586914, "菜谱": []},
{"餐厅名": "山姆老爹烤肉牛排自助体验馆", "经度": 30.65617, "纬度": 104.077663, "图片": "//p0.meituan.net/deal/8b830cfd986b6eb2d570b21548fcdeb5344731.jpg", "depth": 2, "download_timeout": 180.0, "download_slot": "meishi.meituan.com", "download_latency": 0.09722161293029785, "菜谱": [{"名称": "单人自助", "价格": 65, "图片": "//p1.meituan.net/deal/97122f2ec9f04a875b547845f0962ef6107305.jpg"}]},
{"餐厅名": "老灶房老火锅（晋阳店）", "经度": 30.651616, "纬度": 104.003224, "图片": "https://img.meituan.net/msmerchant/5569eacd1870b5219d2f35ec6c962175167907.jpg", "depth": 2, "download_timeout": 180.0, "download_slot": "meishi.meituan.com", "download_latency": 0.11079120635986328, "菜谱": [{"名称": "精致 2 人餐", "价格": 98, "图片": "//p0.meituan.net/deal/4a22a1024d45b928c80e3692d940cde8144361.jpg"}, {"名称": "4 人餐", "价格": 168, "图片": "//p0.meituan.net/deal/4a22a1024d45b928c80e3692d940cde8144361.jpg"}, {"名称": "6至 8 人餐", "价格": 288, "图片": "//p0.meituan.net/deal/4a22a1024d45b928c80e3692d940cde8144361.jpg"}]},
{"餐厅名": "碳来香三国烤肉海鲜欢乐自助风（春熙店）", "经度": 30.656714, "纬度": 104.078052, "图片": "//p0.meituan.net/deal/__19287354__3425877.jpg", "depth": 2, "download_timeout": 180.0, "download_slot": "meishi.meituan.com", "download_latency": 0.1197514533996582, "菜谱": [{"名称": "单人自助", "价格": 59, "图片": "//p0.meituan.net/deal/8b9bbe9b06ea8f4898673a5968a14a0d93568.jpg"}]},
{"餐厅名": "绝城芋儿鸡（龙湖时代天街店）", "经度": 30.751884, "纬度": 103.921068, "图片": "//p1.meituan.net/deal/d9f5aef2cfe84e608aa5e05aef4df2eb283960.jpg", "depth": 2, "download_timeout": 180.0, "download_slot": "meishi.meituan.com", "download_latency": 0.09887385368347168, "菜谱": [{"名称": "双人套餐", "价格": 65, "图片": "//p1.meituan.net/deal/1b9dcaf5223827cbf9d9fc783052c13036585.jpg"}, {"名称": "鲜锅兔 2-3 人餐", "价格": 55, "图片": "//p0.meituan.net/deal/cef3748235b1bcf197efe4754aced7b3137586.jpg"}]},
{"餐厅名": "签王之王（总府路店）", "经度": 30.658129, "纬度": 104.080319, "图片": "https://img.meituan.net/msmerchant/a8a060f450970dac998cd0850e23a5ab377291.png", "depth": 2, "download_timeout": 180.0, "download_slot": "meishi.meituan.com", "download_latency": 0.10375094413757324, "菜谱": [{"名称": "2至 4 人餐", "价格": 128, "图片": "//p1.meituan.net/deal/111f23c39d9bc388de2ef40d6d90248336284.jpeg"}]},
{"餐厅名": "蜀大侠火锅（总府路店）", "经度": 30.65803, "纬度": 104.079073, "图片": "https://img.meituan.net/msmerchant/40b930e907dbdf8a78ef07552c6164f3470847.jpg", "depth": 2, "download_timeout": 180.0, "download_slot": "meishi.meituan.com", "download_latency": 0.09907197952270508, "菜谱": []},
{"餐厅名": "银鲨国际美食百汇（锦华店）", "经度": 30.620762, "纬度": 104.097028, "图片": "https://img.meituan.net/180.180/msmerchant/f751f8aae96231488cf4a296a0a36fdc314604.jpg", "depth": 2, "download_timeout": 180.0, "download_slot": "meishi.meituan.com", "download_latency": 0.09225893020629883, "菜谱": [{"名称": "单人自助晚餐", "价格": 157, "图片": "//p1.meituan.net/deal/5278d770fc48b497dd93dbbefa3688e9101701.jpg"}, {"名称": "单人午市自助", "价格": 137, "图片": "//p1.meituan.net/deal/5278d770fc48b497dd93dbbefa3688e9101701.jpg"}]},
{"餐厅名": "四川皇三爷火锅（全国总店）", "经度": 30.579771, "纬度": 103.918956, "图片": "https://img.meituan.net/msmerchant/2482e03c2ec5fac031368daf9e4e049d539278.jpg", "depth": 2, "download_timeout": 180.0, "download_slot": "meishi.meituan.com", "download_latency": 0.19719934463500977, "菜谱": []},
{"餐厅名": "爱客得海鲜自助烤肉·涮涮锅（春熙路店）", "经度": 30.656884, "纬度": 104.077095, "图片": "https://img.meituan.net/msmerchant/2d2cf06cb55da7f35b4028a0f755186341992.jpg", "depth": 2, "download_timeout": 180.0, "download_slot": "meishi.meituan.com", "download_latency": 0.09541749954223633, "菜谱": [{"名称": "单人自助海鲜烤肉", "价格": 59, "图片": "//p0.meituan.net/deal/__19639639__5813377.jpg"}, {"名称": "10 人海鲜烤肉", "价格": 580, "图片": "//p1.meituan.net/deal/__31024493__7844076.jpg"}, {"名称": "6 人自助海鲜烤肉", "价格": 350, "图片": "//p0.meituan.net/deal/__30172321__3652739.jpg"}, {"名称": "单人海鲜自助烤肉", "价格": 350, "图片": "//p0.meituan.net/deal/__19639642__7762023.jpg"}, {"名称": "爱客得海鲜自助", "价格": 580, "图片": "//p0.meituan.net/deal/__49709754__1426054.jpg"}]}
]